irisml/tasks/create_timm_model.py
irisml/tasks/create_timm_transform.py
irisml_tasks_timm-0.0.1.dist-info/LICENSE
irisml_tasks_timm-0.0.1.dist-info/METADATA
irisml_tasks_timm-0.0.1.dist-info/WHEEL
irisml_tasks_timm-0.0.1.dist-info/top_level.txt
irisml_tasks_timm-0.0.1.dist-info/RECORD
