Metadata-Version: 2.1
Name: irisml-tasks-timm
Version: 0.0.1
Summary: IrisML tasks to use timm library
Author: irisdev
License: MIT
Requires-Python: >=3.8
License-File: LICENSE
Requires-Dist: irisml
Requires-Dist: timm (<1)
